tflite/ATan2Options.py
tflite/AbsOptions.py
tflite/ActivationFunctionType.py
tflite/AddNOptions.py
tflite/AddOptions.py
tflite/ArgMaxOptions.py
tflite/ArgMinOptions.py
tflite/AssignVariableOptions.py
tflite/BatchMatMulOptions.py
tflite/BatchToSpaceNDOptions.py
tflite/BidirectionalSequenceLSTMOptions.py
tflite/BidirectionalSequenceRNNOptions.py
tflite/BroadcastToOptions.py
tflite/BucketizeOptions.py
tflite/Buffer.py
tflite/BuiltinOperator.py
tflite/BuiltinOptions.py
tflite/CallOnceOptions.py
tflite/CallOptions.py
tflite/CastOptions.py
tflite/CombinerType.py
tflite/ConcatEmbeddingsOptions.py
tflite/ConcatenationOptions.py
tflite/Conv2DOptions.py
tflite/Conv3DOptions.py
tflite/CosOptions.py
tflite/CumsumOptions.py
tflite/CustomOptionsFormat.py
tflite/CustomQuantization.py
tflite/DensifyOptions.py
tflite/DepthToSpaceOptions.py
tflite/DepthwiseConv2DOptions.py
tflite/DequantizeOptions.py
tflite/DimensionMetadata.py
tflite/DimensionType.py
tflite/DivOptions.py
tflite/DynamicUpdateSliceOptions.py
tflite/EmbeddingLookupSparseOptions.py
tflite/EqualOptions.py
tflite/ExpOptions.py
tflite/ExpandDimsOptions.py
tflite/FakeQuantOptions.py
tflite/FillOptions.py
tflite/FloorDivOptions.py
tflite/FloorModOptions.py
tflite/FullyConnectedOptions.py
tflite/FullyConnectedOptionsWeightsFormat.py
tflite/GatherNdOptions.py
tflite/GatherOptions.py
tflite/GeluOptions.py
tflite/GreaterEqualOptions.py
tflite/GreaterOptions.py
tflite/HardSwishOptions.py
tflite/HashtableFindOptions.py
tflite/HashtableImportOptions.py
tflite/HashtableOptions.py
tflite/HashtableSizeOptions.py
tflite/IfOptions.py
tflite/Int32Vector.py
tflite/L2NormOptions.py
tflite/LSHProjectionOptions.py
tflite/LSHProjectionType.py
tflite/LSTMKernelType.py
tflite/LSTMOptions.py
tflite/LeakyReluOptions.py
tflite/LessEqualOptions.py
tflite/LessOptions.py
tflite/LocalResponseNormalizationOptions.py
tflite/LogSoftmaxOptions.py
tflite/LogicalAndOptions.py
tflite/LogicalNotOptions.py
tflite/LogicalOrOptions.py
tflite-2.10.0.dist-info/LICENSE
tflite-2.10.0.dist-info/METADATA
tflite-2.10.0.dist-info/WHEEL
tflite-2.10.0.dist-info/top_level.txt
tflite-2.10.0.dist-info/RECORD
