Metadata-Version: 2.1
Name: tflite
Version: 2.10.0
Summary: Parsing TensorFlow Lite Models (*.tflite) Easily
Home-page: https://zhenhuaw.me/tflite
Author: 王振华(Zhenhua WANG)
Author-email: hi@zhenhuaw.me
License: Apache License 2.0
Project-URL: Bug Reports, https://github.com/zhenhuaw-me/tflite/issues
Project-URL: Source, https://github.com/zhenhuaw-me/tflite
Keywords: tflite,tensorflow
Classifier: Development Status :: 4 - Beta
Classifier: Programming Language :: Python :: 2
Classifier: Programming Language :: Python :: 2.7
Classifier: Programming Language :: Python :: 3
Classifier: Programming Language :: Python :: 3.5
Classifier: Programming Language :: Python :: 3.6
Classifier: Programming Language :: Python :: 3.7
Classifier: Environment :: Console
Classifier: Intended Audience :: Developers
Classifier: License :: OSI Approved :: Apache Software License
Classifier: Natural Language :: English
Classifier: Operating System :: OS Independent
Classifier: Topic :: Scientific/Engineering :: Artificial Intelligence
Requires-Python: !=3.0.*,!=3.1.*,!=3.2.*,!=3.3.*,!=3.4.*,<4,>=2.7
License-File: LICENSE
